Workbook

Sheet Export Summary
B3: This document was exported from Numbers. Each table was converted to an Excel worksheet. All other objects on each Numbers sheet were placed on separate worksheets. Please be aware that formula calculations may differ in Excel.
B7: Numbers Sheet Name | C7: Numbers Table Name | D7: Excel Worksheet Name
B9: Analysis
C10: Table 1 | D10: Analysis
B11: 5 Year Projected
C12: Table 1 | D12: 5 Year Projected

Sheet Analysis
A1: Short Term Rental Property Analysis:
A3: Property Info: | F3: Purchase: | K3: Expenses:
A4: Address: | B4: 4728 Avenida La Manana | F4: Asking Price: | G4: 825000 | K4: Mortgage Amount: | L4: =G5-G7 -> 639200
A5: City: | B5: Joshua Tree | F5: Offer Price: | G5: 799000 | K5: Term: (Years) | L5: 30
A6: State: | B6: CA | F6: Down Payment (%): | G6: 0.2 | K6: # of Payments: | L6: =L5*12 -> 360
A7: Zip Code: | B7: 92252 | F7: Down Payment ($): | G7: =G6*G5 -> 159800 | K7: Interest Rate (%): | L7: 0.065
A8: Bedroom: | B8: Studio | F8: Estimated Closing Cost (%): | G8: 0.03 | K8: Monthly Principle/Interest: | L8: =PMT(L7/12,L6,L4)*-1 -> 4040.1788
A9: Bath: | B9: 1 | F9: Estimated Closing Cost ($): | G9: =G8*G5 -> 23970 | K9: Estimated Property Tax (Yr): | L9: =L10*12 -> 9588
A10: Square Feet: | B10: 391 | F10: Renovation Cost: | G10: 0 | K10: Estimated Property Tax (Mo): | L10: 799
A11: Subdivision: | F11: Setup Cost: | G11: 45000 | K11: Estimated Insurance: (Yr) | L11: =L12*12 -> 3360
A12: Year Built: | B12: 2021 | F12: Total Investment: | G12: =G10+G9+G7+G11 -> 228770 | K12: Estimated Insurance: (Mo) | L12: 280
A13: Other Info: | K13: Private Mortgage Insurance (Yr): | L13: =L14*12 -> 0
F14: Income: | K14: Private Mortgage Insurance (Mo): | L14: 0
A15: Comments: | F15: Gross Income (Yr): | G15: =G16*12 -> 117912.9 | K15: Monthly HOA: | L15: 0
F16: Gross Income (Mo): | G16: =((G17*365)/12*G18)+G19 -> 9826.075 | K16: Estimated Monthly Utilites: (Water/Elec/Gas) | L16: 450
F17: Average Nightly Rate: | G17: 438 | K17: AirBNB Fee (Yr): 3% | L17: =L18*12 -> 3537.387
F18: Average Occupancy: | G18: 0.67 | K18: AirBNB Fee (Mo): 3% | L18: =G16*0.03 -> 294.78225
F19: Cleaning Fee (Mo): | G19: 900 | K19: Cleaning Fee (Mo): | L19: 900
F20: Net Operating Income: | G20: =G15-L28 -> 75458.481 | K20: Cable/Internet (Mo): | L20: 100
F21: Cap Rate: | G21: =G20/G5 -> 0.094441153 | K21: Repairs/Maintenance (Mo) (%) | L21: 0.05
F22: Cash Flow (Yr): | G22: =G23*12 -> 26976.335 | K22: Repairs/Maintenance (Mo) ($) | L22: =((G17*365)/12*G18)*L21 -> 446.30375
F23: Cash Flow (Mo): | G23: =(G16-L31) -> 2248.0279 | K23: Management Fee (Mo) (%) | L23: 0.03
F24: Cash on Cash Return: | G24: =(G22)/(G12) -> 0.11791902 | K24: Management Fee (Mo) ($) | L24: =((G17*365)/12*G18)*L23 -> 267.78225
F27: User Input:
F28: Calculated: | K28: Operating Expenses: (Annual) | L28: =L29*12 -> 42454.419
K29: Operating Expenses: (Monthly) | L29: =L10+L12+L14+L15+L16+L18+L19+L20+L22+L24 -> 3537.8682
K30: Total Expenses: (Annual) | L30: =L31*12 -> 90936.565
K31: Total Expenses: (Monthly) | L31: =L29+L8 -> 7578.0471

Sheet 5 Year Projected
D1: Projected Year 1: | E1: Projected Year 2: | F1: Projected Year 3: | G1: Projected Year 4: | H1: Projected Year 5:
A2: Annual Increase in Gross Income: (%) | E2: 0.02 | F2: 0.02 | G2: 0.02 | H2: 0.02
A3: Annual Increase in Operating Expenses: (%) | E3: 0.03 | F3: 0.03 | G3: 0.03 | H3: 0.03
A4: Annual Appreciation: (%) | E4: 0.03 | F4: 0.03 | G4: 0.03 | H4: 0.03
I5: 5 YEAR TOTALS:
A6: Annual Gross Rental Income: | D6: ='Analysis'!G15 -> 117912.9 | E6: =D6+(D6*E2) -> 120271.16 | F6: =E6+(E6*F2) -> 122676.58 | G6: =F6+(F6*G2) -> 125130.11 | H6: =G6+(G6*H2) -> 127632.72 | I6: Total Annual Gross Income: | J6: =SUM(D6:H6) -> 613623.47
A7: Annual Operating Expenses: | D7: ='Analysis'!L28 -> 42454.419 | E7: =D7+(D7*E3) -> 43728.052 | F7: =E7+(E7*F3) -> 45039.893 | G7: =F7+(F7*G3) -> 46391.09 | H7: =G7+(G7*H3) -> 47782.823 | I7: Total Operating Expenses: | J7: =SUM(D7:H7) -> 225396.28
A8: Mortage Debt: | D8: ='Analysis'!$L$8*12 -> 48482.146 | E8: ='Analysis'!$L$8*12 -> 48482.146 | F8: ='Analysis'!$L$8*12 -> 48482.146 | G8: ='Analysis'!$L$8*12 -> 48482.146 | H8: ='Analysis'!$L$8*12 -> 48482.146 | I8: Total Mortgage Payments: | J8: =SUM(D8:H8) -> 242410.73
A10: Cash Flow: | D10: =D6-D7-D8 -> 26976.335 | E10: =E6-E7-E8 -> 28060.961 | F10: =F6-F7-F8 -> 29154.542 | G10: =G6-G7-G8 -> 30256.877 | H10: =H6-H7-H8 -> 31367.747 | I10: Total Cash Flow: | J10: =SUM(D10:H10) -> 145816.46
A11: Monthly Cash Flow: | D11: =D10/12 -> 2248.0279 | E11: =E10/12 -> 2338.4134 | F11: =F10/12 -> 2429.5452 | G11: =G10/12 -> 2521.4064 | H11: =H10/12 -> 2613.9789 | I11: Average Monthly CF: | J11: =SUM(D11:H11)/5 -> 2430.2744
A12: CoC Return from Initial Investment: | D12: =D10/'Analysis'!$G$12 -> 0.11791902 | E12: =E10/'Analysis'!$G$12 -> 0.12266014 | F12: =F10/'Analysis'!$G$12 -> 0.12744041 | G12: =G10/'Analysis'!$G$12 -> 0.13225894 | H12: =H10/'Analysis'!$G$12 -> 0.13711477
A13: Property Value: | D13: ='Analysis'!G5 -> 799000 | E13: =D13+(D13*E4) -> 822970 | F13: =E13+(E13*F4) -> 847659.1 | G13: =F13+(F13*G4) -> 873088.87 | H13: =G13+(G13*H4) -> 899281.54 | I13: Increase In Value: | J13: =H13-D13 -> 100281.54
A14: Amount Owed: | D14: =D23 -> 632265.85 | E14: =E23 -> 624880.99 | F14: =F23 -> 617016.11 | G14: =G23 -> 608640.01 | H14: =H23 -> 599719.46 | I14: Mortgage Paydown: | J14: =H14-D14 -> -32546.39
A15: Equity: | D15: =SUM(D13-D14) -> 166734.15 | E15: =SUM(E13-E14) -> 198089.01 | F15: =SUM(F13-F14) -> 230642.99 | G15: =SUM(G13-G14) -> 264448.86 | H15: =SUM(H13-H14) -> 299562.08 | I15: Appreciation + Cash flow: | J15: =J13+J10 -> 246098
B18: Mortgage Breakdown: | I18: Return on Initial Investment: | J18: =J15/'Analysis'!G12 -> 1.0757442
B19: Mortgage Amount: | D19: ='Analysis'!$L$4 -> 639200 | E19: =D23 -> 632265.85 | F19: =E23 -> 624880.99 | G19: =F23 -> 617016.11 | H19: =G23 -> 608640.01
B20: I: (Monthly) | D20: ='Analysis'!$L$7/12 -> 0.0054166667 | E20: ='Analysis'!$L$7/12 -> 0.0054166667 | F20: ='Analysis'!$L$7/12 -> 0.0054166667 | G20: ='Analysis'!$L$7/12 -> 0.0054166667 | H20: ='Analysis'!$L$7/12 -> 0.0054166667
B21: Monthly Payment: | D21: =PMT(D20,'Analysis'!$L$6,-$D$19,0)*12 -> 48482.146 | E21: =PMT(E20,'Analysis'!$L$6,-$D$19,0)*12 -> 48482.146 | F21: =PMT(F20,'Analysis'!$L$6,-$D$19,0)*12 -> 48482.146 | G21: =PMT(G20,'Analysis'!$L$6,-$D$19,0)*12 -> 48482.146 | H21: =PMT(H20,'Analysis'!$L$6,-$D$19,0)*12 -> 48482.146 | I21: Net Proceeds after Sale: (4% Agent Commision) | J21: =H13-(H13*0.04)-H14 -> 263590.81
B22: Interest: | D22: =D19*D20*12 -> 41548 | E22: =E19*E20*12 -> 41097.281 | F22: =F19*F20*12 -> 40617.264 | G22: =G19*G20*12 -> 40106.047 | H22: =H19*H20*12 -> 39561.601
B23: Principal Paydown: | D23: =D19-D21+D22 -> 632265.85 | E23: =E19-E21+E22 -> 624880.99 | F23: =F19-F21+F22 -> 617016.11 | G23: =G19-G21+G22 -> 608640.01 | H23: =H19-H21+H22 -> 599719.46
